dfmock/__init__.py
dfmock/__main__.py
dfmock/dfmock.py
dfmock-0.0.14.dist-info/METADATA
dfmock-0.0.14.dist-info/WHEEL
dfmock-0.0.14.dist-info/top_level.txt
dfmock-0.0.14.dist-info/RECORD
