Metadata-Version: 2.1
Name: dfmock
Version: 0.0.14
Summary: utility for generating mock data sets as pandas dataframes
Home-page: https://github.com/integrichain1/dfmock
Author: Integrichain Innovation Team
Author-email: engineering@integrichain.com
License: MIT
Platform: UNKNOWN
Classifier: License :: OSI Approved :: MIT License
Classifier: Programming Language :: Python :: 3
Classifier: Programming Language :: Python :: 3.7
Requires-Dist: pandas
